README.rst
setup.py
pyuploadcare_wtforms/__init__.py
pyuploadcare_wtforms/fields.py
pyuploadcare_wtforms.egg-info/PKG-INFO
pyuploadcare_wtforms.egg-info/SOURCES.txt
pyuploadcare_wtforms.egg-info/dependency_links.txt
pyuploadcare_wtforms.egg-info/requires.txt
pyuploadcare_wtforms.egg-info/top_level.txt