Metadata-Version: 1.1
Name: pyuploadcare-wtforms
Version: 0.5
Summary: Custom fields for working with Uploadcare service.
Home-page: https://github.com/uploadcare/pyuploadcare-wtforms
Author: Uploadcare LLC
Author-email: hello@uploadcare.com
License: MIT
Keywords: pyuploadcare wtforms
Platform: UNKNOWN
Classifier: Development Status :: 4 - Beta
Classifier: Intended Audience :: Developers
Classifier: License :: OSI Approved :: MIT License
Classifier: Natural Language :: English
Classifier: Programming Language :: Python :: 2
Classifier: Programming Language :: Python :: 2.6
Classifier: Programming Language :: Python :: 2.7
Classifier: Programming Language :: Python :: 3
Classifier: Programming Language :: Python :: 3.3
Classifier: Programming Language :: Python :: 3.4
